{
  "id": "058",
  "text": "Минимизация переключений контекста",
  "categories": [
    "processes"
  ],
  "tags": [
    "задачи"
  ],
  "categories_info": [
    {
      "key": "processes",
      "title": "Процессы разработки",
      "description": "Методологии и практики работы команды"
    }
  ],
  "contexts": {
    "processes": {
      "subcategories": [
        "Работа с задачами"
      ],
      "descriptions": {
        "Работа с задачами": "Минимизация контекстных переключений между задачами"
      }
    }
  }
}